hyfetch/__init__.py
hyfetch/__main__.py
hyfetch/__version__.py
hyfetch/color_scale.py
hyfetch/color_util.py
hyfetch/constants.py
hyfetch/font_logo.py
hyfetch/main.py
hyfetch/models.py
hyfetch/neofetch_util.py
hyfetch/presets.py
hyfetch/pride_month.py
hyfetch/py.py
hyfetch/rs.py
hyfetch/serializer.py
hyfetch/termenv.py
hyfetch/types.py
hyfetch/data/font_logos.json
hyfetch/data/presets.json
hyfetch/distros/__init__.py
hyfetch/distros/adelie.py
hyfetch/distros/aeros.py
hyfetch/distros/afterglow.py
hyfetch/distros/aix.py
hyfetch/distros/almalinux.py
hyfetch/distros/alpine.py
hyfetch/distros/alpine_small.py
hyfetch/distros/alter.py
hyfetch/distros/amazon.py
hyfetch/distros/amogos.py
hyfetch/distros/anarchy.py
hyfetch/distros/android.py
hyfetch/distros/android_small.py
hyfetch/distros/antergos.py
hyfetch/distros/antix.py
hyfetch/distros/aosc_os.py
hyfetch/distros/aperio_gnu_linux.py
hyfetch/distros/aperture.py
hyfetch/distros/apricity.py
hyfetch/distros/arch.py
hyfetch/distros/arch_old.py
hyfetch/distros/arch_small.py
hyfetch/distros/archbox.py
hyfetch/distros/archcraft.py
hyfetch/distros/archcraft_ascii.py
hyfetch/distros/archcraft_minimal.py
hyfetch/distros/archlabs.py
hyfetch/distros/archmerge.py
hyfetch/distros/archstrike.py
hyfetch/distros/arcolinux.py
hyfetch/distros/arcolinux_small.py
hyfetch/distros/arkane.py
hyfetch/distros/arselinux.py
hyfetch/distros/artix.py
hyfetch/distros/artix_small.py
hyfetch/distros/arya.py
hyfetch/distros/asahi.py
hyfetch/distros/asteroidos.py
hyfetch/distros/astos.py
hyfetch/distros/astra_linux.py
hyfetch/distros/athena.py
hyfetch/distros/azos.py
hyfetch/distros/bazzite.py
hyfetch/distros/bedrock.py
hyfetch/distros/biglinux.py
hyfetch/distros/biglinux_large.py
hyfetch/distros/bitrig.py
hyfetch/distros/blackarch.py
hyfetch/distros/blackmesa.py
hyfetch/distros/blackpanther.py
hyfetch/distros/blag.py
hyfetch/distros/blankon.py
hyfetch/distros/bluelight.py
hyfetch/distros/bodhi.py
hyfetch/distros/bonsai.py
hyfetch/distros/bsd.py
hyfetch-2.0.4.dist-info/METADATA
hyfetch-2.0.4.dist-info/WHEEL
hyfetch-2.0.4.dist-info/entry_points.txt
hyfetch-2.0.4.dist-info/licenses/LICENSE.md
hyfetch-2.0.4.dist-info/RECORD
