Metadata-Version: 2.4
Name: HyFetch
Version: 2.0.4
Summary: neofetch with flags <3
Project-URL: Homepage, https://github.com/hykilpikonna/HyFetch
Author-email: Azalea Gui <me@hydev.org>
License-Expression: MIT
License-File: LICENSE.md
Classifier: License :: OSI Approved :: MIT License
Classifier: Programming Language :: Python :: 3
Classifier: Programming Language :: Python :: 3.7
Classifier: Programming Language :: Python :: 3.8
Classifier: Programming Language :: Python :: 3.9
Classifier: Programming Language :: Python :: 3.10
Classifier: Programming Language :: Python :: 3.11
Classifier: Programming Language :: Python :: 3.12
Classifier: Programming Language :: Python :: 3.13
Requires-Python: >=3.7
Requires-Dist: colorama>=0.4.6; platform_system == 'Windows'
Requires-Dist: psutil; platform_system == 'Windows'
Requires-Dist: typing-extensions; python_version < '3.8'
